funimg/__init__.py
funimg/images.py
funimg-0.0.3.dist-info/METADATA
funimg-0.0.3.dist-info/WHEEL
funimg-0.0.3.dist-info/top_level.txt
funimg-0.0.3.dist-info/RECORD
