Metadata-Version: 2.1
Name: funimg
Version: 0.0.3
Summary: A small package to manipulate images with preloaded images
Home-page: UNKNOWN
Author: devhubyt
Author-email: devhubyt@gmail.com
License: UNKNOWN
Platform: UNKNOWN
Classifier: Programming Language :: Python :: 3
Classifier: License :: OSI Approved :: MIT License
Classifier: Operating System :: OS Independent
Requires-Python: >=3.6
